eggscript/__init__.py
eggscript/parse.py
eggscript/version.py
ovos_eggscript-0.0.0.dist-info/METADATA
ovos_eggscript-0.0.0.dist-info/WHEEL
ovos_eggscript-0.0.0.dist-info/top_level.txt
ovos_eggscript-0.0.0.dist-info/zip-safe
ovos_eggscript-0.0.0.dist-info/RECORD
