Metadata-Version: 2.1
Name: ovos-eggscript
Version: 0.0.0
Summary: UNKNOWN
Home-page: https://github.com/OpenVoiceOS/eggscript
Author: jarbasai
Author-email: jarbasai@mailfence.com
License: MIT
Keywords: ovos skill builder
Platform: UNKNOWN
